tkintertoy/Shipman_tkinter8_5.pdf
tkintertoy/__init__.py
tkintertoy/tt.py
tkintertoy/ttgallery.py
tkintertoy-1.6.2.dist-info/LICENSE
tkintertoy-1.6.2.dist-info/METADATA
tkintertoy-1.6.2.dist-info/WHEEL
tkintertoy-1.6.2.dist-info/top_level.txt
tkintertoy-1.6.2.dist-info/RECORD
