Metadata-Version: 2.1
Name: tkintertoy
Version: 1.6.2
Summary: A simple GUI package based on Tkinter
Author-email: Mike Callahan <mcalla@twc.com>
Project-URL: Homepage, https://github.com/mcalla314/tkintertoy
Project-URL: Documentation, https://tkintertoy.readthedocs.io
Keywords: GUI,novice
Classifier: Programming Language :: Python :: 3 :: Only
Classifier: License :: OSI Approved :: MIT License
Classifier: Operating System :: OS Independent
Classifier: Intended Audience :: Education
Classifier: Topic :: Software Development :: User Interfaces
Requires-Python: >=3.7
License-File: LICENSE
